.gitignore
README.rst
cisVar.py
regression_qtls.R
setup.py
cisVar.egg-info/PKG-INFO
cisVar.egg-info/SOURCES.txt
cisVar.egg-info/dependency_links.txt
cisVar.egg-info/entry_points.txt
cisVar.egg-info/requires.txt
cisVar.egg-info/top_level.txt
pipeline/Snakefile
pipeline/cisvar_config.json
pipeline/cisvar_samples.json
pipeline/cluster.json
scripts/combine.py
scripts/plot_fun.R
scripts/rmdup.py