Metadata-Version: 1.1
Name: cisVar
Version: 2.0.0b3
Summary: Calculate both pre and post frequencies for ChIP or ATAC style data
Home-page: https://github.com/TheFraserLab/cisVar
Author: Ashley Tehranchi
Author-email: mike.dacre@gmail.com
License: MIT
Download-URL: https://github.com/TheFraserLab/cisVar/archive/v2.0.0b3.tar.gz
Keywords: ATACseq ChIPseq regression bioinformatics
Platform: UNKNOWN
Classifier: Development Status :: 4 - Beta
Classifier: Environment :: Console
Classifier: Intended Audience :: End Users/Desktop
Classifier: Intended Audience :: Science/Research
Classifier: License :: OSI Approved :: MIT License
Classifier: Natural Language :: English
Classifier: Operating System :: MacOS :: MacOS X
Classifier: Operating System :: POSIX
Classifier: Programming Language :: Python
Classifier: Programming Language :: Python :: 2
Classifier: Programming Language :: Python :: 3
Classifier: Topic :: Utilities
Requires: pandas
Requires: numpy
Requires: scipy
Requires: psutil
Requires: snakemake
Requires: wget
